opnsense_prom_exporter-1.1.0-py3.11-nspkg.pth
opnsense_exporter/opnsense_api.py
opnsense_exporter/server.py
opnsense_prom_exporter-1.1.0.dist-info/LICENSE
opnsense_prom_exporter-1.1.0.dist-info/METADATA
opnsense_prom_exporter-1.1.0.dist-info/WHEEL
opnsense_prom_exporter-1.1.0.dist-info/entry_points.txt
opnsense_prom_exporter-1.1.0.dist-info/namespace_packages.txt
opnsense_prom_exporter-1.1.0.dist-info/top_level.txt
opnsense_prom_exporter-1.1.0.dist-info/RECORD
