Metadata-Version: 2.1
Name: opnsense-prom-exporter
Version: 1.1.0
Summary: OPNSense Prometheus exporter
Home-page: https://gitlab.com/micro-entreprise/opnsense-prom-exporter
Author: Pierre Verkest
Author-email: pierreverkest84@gmail.com
License: Apache-2.0
Classifier: Development Status :: 5 - Production/Stable
Classifier: Programming Language :: Python :: 3
Classifier: License :: OSI Approved :: Apache Software License
License-File: LICENSE
Requires-Dist: prometheus-client
Requires-Dist: python-dotenv
Requires-Dist: requests
